{
  "vct": "urn:eudi:micro_credential:1",
  "name": "MicroCredential",
  "description": "MicroCredential.",
  "$comment": "",
  "display": [
    {
      "lang": "en-US",
      "name": "MicroCredential",
      "description": "Portable microcredential.",
      "rendering": {
        "svg_templates": [
          {
            "uri": "https://raw.githubusercontent.com/dc4eu/vc/8e0066324edbdcf468d3337ce6d1d9a150b4be4f/images/micro-credential-plain.svg",
            "uri#integrity": "sha256-qqYKI79lQYmCrYl/4fryslc4IH1GxPSgQ1yNnz+7IzY=",
            "properties": {
            }
          }
        ]
      }
    }
  ],
  "claims": [
            {
      "path": [
        "credentialSubject",
        "achievement",
        "name"
      ],
      "sd": "never",
      "svg_id": "achievementName",
      "display": [
        {
          "lang": "en-US",
          "label": "Name",
          "description": "name of the achievement."
        }
      ]
    },
            {
      "path": [
        "credentialSubject",
        "achievement",
        "description"
      ],
      "sd": "never",
      "svg_id": "achievementDescription",
      "display": [
        {
          "lang": "en-US",
          "label": "Description",
          "description": "description of the achievement."
        }
      ]
    },
            {
      "path": [
        "credentialSubject",
        "achievement",
        "criteria",
        "narrative"
      ],
      "sd": "never",
      "svg_id": "criteriaNarrative",
      "display": [
        {
          "lang": "en-US",
          "label": "criteriaNarrative",
          "description": "criteriaNarrative of the achievement."
        }
      ]
    },
            {
      "path": [
        "credentialSubject",
        "achievement",
        "ECTS"
      ],
      "sd": "never",
      "svg_id": "achievementECTS",
      "display": [
        {
          "lang": "en-US",
          "label": "achievementECTS",
          "description": "achievementECTS of the achievement."
        }
      ]
    },
            {
      "path": [
        "Issuer",
        "Name"
      ],
      "sd": "never",
      "svg_id": "issuerName",
      "display": [
        {
          "lang": "en-US",
          "label": "Issuer Name",
          "description": "Name of the issuer of the microcredential."
        }
      ]
    }
  ],
  "schema_uri": "",
  "schema_uri#integrity": ""
}
